LICENSE
MANIFEST.in
README.rst
requirements.txt
setup.cfg
setup.py
ckanext/__init__.py
ckanext/odi_certificates_store/__init__.py
ckanext/odi_certificates_store/command.py
ckanext/odi_certificates_store/jobs.py
ckanext/odi_certificates_store/plugin.py
ckanext/odi_certificates_store/lib/__init__.py
ckanext/odi_certificates_store/lib/package_odi_certificate.py
ckanext/odi_certificates_store/logic/__init__.py
ckanext/odi_certificates_store/logic/action/__init__.py
ckanext/odi_certificates_store/logic/action/update.py
ckanext/odi_certificates_store/tests/__init__.py
ckanext/odi_certificates_store/tests/test_plugin.py
ckanext_odi_certificates_store.egg-info/PKG-INFO
ckanext_odi_certificates_store.egg-info/SOURCES.txt
ckanext_odi_certificates_store.egg-info/dependency_links.txt
ckanext_odi_certificates_store.egg-info/entry_points.txt
ckanext_odi_certificates_store.egg-info/namespace_packages.txt
ckanext_odi_certificates_store.egg-info/top_level.txt